turtle_fr.py
turtle_fr-1.0.6.dist-info/METADATA
turtle_fr-1.0.6.dist-info/WHEEL
turtle_fr-1.0.6.dist-info/top_level.txt
turtle_fr-1.0.6.dist-info/RECORD
