Metadata-Version: 2.1
Name: turtle_fr
Version: 1.0.6
Summary: Version simplifée en français du module turtle
Home-page: https://github.com/bouquet-cedric/module-python
Author: Bouquet Cédric
Author-email: cedric-bouquet-7@outlook.fr
Classifier: Programming Language :: Python :: 3
Requires: tkinter
Requires: PIL
Requires-Python: >=3.0
